{
  "kind": "unatomo-nfc-backup-status",
  "firestore": {
    "status": "ok",
    "completedAt": "2026-06-17T20:40:00.015Z",
    "file": ".backups/2026-06-17T20-40-00-016Z-nfc-firestore.json",
    "projectId": "unatomo-c20a4",
    "collectionCount": 11,
    "documentCount": 274,
    "collections": {
      "machines": 58,
      "dashboard_layout": 3,
      "machine_access": 40,
      "tags": 41,
      "admin_machine_links": 50,
      "admin_machine_invites": 59,
      "machine_transfer_invites": 1,
      "users": 7,
      "account_directory": 7,
      "dashboard_suggestions": 1,
      "registration_codes": 7
    }
  },
  "storage": {
    "status": "ok",
    "completedAt": "2026-06-17T20:43:12.648Z",
    "file": ".backups/2026-06-17T20-42-45-685Z-nfc-storage-inventory.json",
    "projectId": "unatomo-c20a4",
    "bucket": "unatomo-c20a4.firebasestorage.app",
    "prefixCount": 2,
    "fileCount": 57,
    "downloadedCount": 57,
    "totalBytes": 33624709,
    "downloadDir": ".backups/2026-06-17T20-42-45-685Z-nfc-storage-files",
    "prefixes": {
      "machine-docs/": {
        "count": 18,
        "totalBytes": 33518314
      },
      "tag-qrs/": {
        "count": 39,
        "totalBytes": 106395
      }
    }
  },
  "updatedAt": "2026-06-17T20:43:12.654Z"
}
